Workbook

Sheet Tbl 1.2
A1: Employment Title | B1: 2024 National Employment Matrix (SOC) code | C1: SOC Code Category | D1: Occupation type | E1: AIOE | F1: Employment, 2024 | G1: Employment, 2034 | H1: Employment distribution, percent, 2024 | I1: Employment distribution, percent, 2034 | J1: Employment change, numeric, 2024–34 | K1: Employment change, percent, 2024–34 | L1: Percent self employed, 2024 | M1: Occupational openings, 2024–34 annual average | N1: Median annual wage, dollars, 2024[1] | O1: Wage Category | P1: Typical education needed for entry
A2: Education administrators, postsecondary | B2: 11-9033 | C2: 11 | D2: Line item | E2: 1.461149 | F2: 226.6 | G2: 230.5 | H2: 0.1 | I2: 0.1 | J2: 4 | K2: 1.7 | L2: 2.2 | M2: 15.1 | N2: 103960 | O2: {=_xlfn.IFS(N2<45000,"Under 45K",N2<75000,"45K - 75K",N2<100000,"75K - 100K",N2>=100000,"Over 100K")} -> Over 100K | P2: Master's degree
A3: Financial managers | B3: 11-3031 | C3: 11 | D3: Line item | E3: 1.446232 | F3: 868.6 | G3: 997.4 | H3: 0.5 | I3: 0.6 | J3: 128.8 | K3: 14.8 | L3: 2.4 | M3: 74.6 | N3: 161700 | O3: {=_xlfn.IFS(N3<45000,"Under 45K",N3<75000,"45K - 75K",N3<100000,"75K - 100K",N3>=100000,"Over 100K")} -> Over 100K | P3: Bachelor's degree
A4: Purchasing managers | B4: 11-3061 | C4: 11 | D4: Line item | E4: 1.423426 | F4: 83.5 | G4: 86.1 | H4: 0 | I4: 0 | J4: 2.6 | K4: 3.1 | L4: 0.8 | M4: 6.4 | N4: 139510 | O4: {=_xlfn.IFS(N4<45000,"Under 45K",N4<75000,"45K - 75K",N4<100000,"75K - 100K",N4>=100000,"Over 100K")} -> Over 100K | P4: Bachelor's degree
A5: Chief executives | B5: 11-1011 | C5: 11 | D5: Line item | E5: 1.334246 | F5: 309.4 | G5: 322.7 | H5: 0.2 | I5: 0.2 | J5: 13.3 | K5: 4.3 | L5: 25.9 | M5: 22.2 | N5: 206420 | O5: {=_xlfn.IFS(N5<45000,"Under 45K",N5<75000,"45K - 75K",N5<100000,"75K - 100K",N5>=100000,"Over 100K")} -> Over 100K | P5: Bachelor's degree
A6: Natural sciences managers | B6: 11-9121 | C6: 11 | D6: Line item | E6: 1.327906 | F6: 104.3 | G6: 108.2 | H6: 0.1 | I6: 0.1 | J6: 3.9 | K6: 3.7 | L6: — | M6: 8.5 | N6: 161180 | O6: {=_xlfn.IFS(N6<45000,"Under 45K",N6<75000,"45K - 75K",N6<100000,"75K - 100K",N6>=100000,"Over 100K")} -> Over 100K | P6: Bachelor's degree
A7: Human resources managers | B7: 11-3121 | C7: 11 | D7: Line item | E7: 1.320417 | F7: 221.9 | G7: 233 | H7: 0.1 | I7: 0.1 | J7: 11.1 | K7: 5 | L7: 0.6 | M7: 17.9 | N7: 140030 | O7: {=_xlfn.IFS(N7<45000,"Under 45K",N7<75000,"45K - 75K",N7<100000,"75K - 100K",N7>=100000,"Over 100K")} -> Over 100K | P7: Bachelor's degree
A8: Marketing managers | B8: 11-2021 | C8: 11 | D8: Line item | E8: 1.315032 | F8: 407 | G8: 433.7 | H8: 0.2 | I8: 0.2 | J8: 26.7 | K8: 6.6 | L8: 3.6 | M8: 34.3 | N8: 161030 | O8: {=_xlfn.IFS(N8<45000,"Under 45K",N8<75000,"45K - 75K",N8<100000,"75K - 100K",N8>=100000,"Over 100K")} -> Over 100K | P8: Bachelor's degree
A9: Compensation and benefits managers | B9: 11-3111 | C9: 11 | D9: Line item | E9: 1.298235 | F9: 20.9 | G9: 20.9 | H9: 0 | I9: 0 | J9: 0 | K9: 0.2 | L9: 1.4 | M9: 1.5 | N9: 140360 | O9: {=_xlfn.IFS(N9<45000,"Under 45K",N9<75000,"45K - 75K",N9<100000,"75K - 100K",N9>=100000,"Over 100K")} -> Over 100K | P9: Bachelor's degree
A10: Advertising and promotions managers | B10: 11-2011 | C10: 11 | D10: Line item | E10: 1.294387 | F10: 27 | G10: 26.4 | H10: 0 | I10: 0 | J10: -0.6 | K10: -2.2 | L10: 20.7 | M10: 2.1 | N10: 126960 | O10: {=_xlfn.IFS(N10<45000,"Under 45K",N10<75000,"45K - 75K",N10<100000,"75K - 100K",N10>=100000,"Over 100K")} -> Over 100K | P10: Bachelor's degree
A11: Training and development managers | B11: 11-3131 | C11: 11 | D11: Line item | E11: 1.284423 | F11: 46.4 | G11: 49.2 | H11: 0 | I11: 0 | J11: 2.7 | K11: 5.8 | L11: — | M11: 3.8 | N11: 127090 | O11: {=_xlfn.IFS(N11<45000,"Under 45K",N11<75000,"45K - 75K",N11<100000,"75K - 100K",N11>=100000,"Over 100K")} -> Over 100K | P11: Bachelor's degree
A12: Sales managers | B12: 11-2022 | C12: 11 | D12: Line item | E12: 1.26628 | F12: 619.5 | G12: 648.5 | H12: 0.4 | I12: 0.4 | J12: 29 | K12: 4.7 | L12: 0.9 | M12: 49 | N12: 138060 | O12: {=_xlfn.IFS(N12<45000,"Under 45K",N12<75000,"45K - 75K",N12<100000,"75K - 100K",N12>=100000,"Over 100K")} -> Over 100K | P12: Bachelor's degree
A13: Medical and health services managers | B13: 11-9111 | C13: 11 | D13: Line item | E13: 1.260259 | F13: 616.2 | G13: 759.1 | H13: 0.4 | I13: 0.4 | J13: 142.9 | K13: 23.2 | L13: 5.1 | M13: 62.1 | N13: 117960 | O13: {=_xlfn.IFS(N13<45000,"Under 45K",N13<75000,"45K - 75K",N13<100000,"75K - 100K",N13>=100000,"Over 100K")} -> Over 100K | P13: Bachelor's degree
A14: Property, real estate, and community association managers | B14: 11-9141 | C14: 11 | D14: Line item | E14: 1.215396 | F14: 466.1 | G14: 483.1 | H14: 0.3 | I14: 0.3 | J14: 17 | K14: 3.6 | L14: 34 | M14: 39 | N14: 66700 | O14: {=_xlfn.IFS(N14<45000,"Under 45K",N14<75000,"45K - 75K",N14<100000,"75K - 100K",N14>=100000,"Over 100K")} -> 45K - 75K | P14: High school diploma or equivalent
A15: Social and community service managers | B15: 11-9151 | C15: 11 | D15: Line item | E15: 1.156153 | F15: 219.8 | G15: 233.9 | H15: 0.1 | I15: 0.1 | J15: 14.1 | K15: 6.4 | L15: 5.6 | M15: 18.6 | N15: 78240 | O15: {=_xlfn.IFS(N15<45000,"Under 45K",N15<75000,"45K - 75K",N15<100000,"75K - 100K",N15>=100000,"Over 100K")} -> 75K - 100K | P15: Bachelor's degree
A16: Computer and information systems managers | B16: 11-3021 | C16: 11 | D16: Line item | E16: 1.059853 | F16: 667.1 | G16: 768.7 | H16: 0.4 | I16: 0.4 | J16: 101.6 | K16: 15.2 | L16: 0.9 | M16: 55.6 | N16: 171200 | O16: {=_xlfn.IFS(N16<45000,"Under 45K",N16<75000,"45K - 75K",N16<100000,"75K - 100K",N16>=100000,"Over 100K")} -> Over 100K | P16: Bachelor's degree
A17: Education administrators, kindergarten through secondary | B17: 11-9032 | C17: 11 | D17: Line item | E17: 1.048811 | F17: 333.3 | G17: 328.1 | H17: 0.2 | I17: 0.2 | J17: -5.1 | K17: -1.5 | L17: 1.2 | M17: 20.8 | N17: 104070 | O17: {=_xlfn.IFS(N17<45000,"Under 45K",N17<75000,"45K - 75K",N17<100000,"75K - 100K",N17>=100000,"Over 100K")} -> Over 100K | P17: Master's degree
A18: Emergency management directors | B18: 11-9161 | C18: 11 | D18: Line item | E18: 1.030768 | F18: 13.2 | G18: 13.6 | H18: 0 | I18: 0 | J18: 0.4 | K18: 3 | L18: — | M18: 1 | N18: 86130 | O18: {=_xlfn.IFS(N18<45000,"Under 45K",N18<75000,"45K - 75K",N18<100000,"75K - 100K",N18>=100000,"Over 100K")} -> 75K - 100K | P18: Bachelor's degree
A19: Construction managers | B19: 11-9021 | C19: 11 | D19: Line item | E19: 1.029139 | F19: 550.3 | G19: 598.4 | H19: 0.3 | I19: 0.3 | J19: 48.1 | K19: 8.7 | L19: 35.8 | M19: 46.8 | N19: 106980 | O19: {=_xlfn.IFS(N19<45000,"Under 45K",N19<75000,"45K - 75K",N19<100000,"75K - 100K",N19>=100000,"Over 100K")} -> Over 100K | P19: Bachelor's degree
A20: Managers, all other | B20: 11-9199 | C20: 11 | D20: Line item | E20: 0.9646872 | F20: 1333.7 | G20: 1393.5 | H20: 0.8 | I20: 0.8 | J20: 59.8 | K20: 4.5 | L20: 48.6 | M20: 106.7 | N20: 136550 | O20: {=_xlfn.IFS(N20<45000,"Under 45K",N20<75000,"45K - 75K",N20<100000,"75K - 100K",N20>=100000,"Over 100K")} -> Over 100K | P20: Bachelor's degree
A21: Transportation, storage, and distribution managers | B21: 11-3071 | C21: 11 | D21: Line item | E21: 0.8907923 | F21: 216.7 | G21: 229.8 | H21: 0.1 | I21: 0.1 | J21: 13.1 | K21: 6.1 | L21: 1.7 | M21: 18.5 | N21: 102010 | O21: {=_xlfn.IFS(N21<45000,"Under 45K",N21<75000,"45K - 75K",N21<100000,"75K - 100K",N21>=100000,"Over 100K")} -> Over 100K | P21: High school diploma or equivalent
A22: Education and childcare administrators, preschool and daycare | B22: 11-9031 | C22: 11 | D22: Line item | E22: 0.838007 | F22: 90.2 | G22: 87.9 | H22: 0.1 | I22: 0.1 | J22: -2.3 | K22: -2.5 | L22: 4.9 | M22: 5.5 | N22: 56270 | O22: {=_xlfn.IFS(N22<45000,"Under 45K",N22<75000,"45K - 75K",N22<100000,"75K - 100K",N22>=100000,"Over 100K")} -> 45K - 75K | P22: Bachelor's degree
A23: Architectural and engineering managers | B23: 11-9041 | C23: 11 | D23: Line item | E23: 0.8370105 | F23: 212.5 | G23: 220.5 | H23: 0.1 | I23: 0.1 | J23: 8 | K23: 3.8 | L23: 0.2 | M23: 14.5 | N23: 167740 | O23: {=_xlfn.IFS(N23<45000,"Under 45K",N23<75000,"45K - 75K",N23<100000,"75K - 100K",N23>=100000,"Over 100K")} -> Over 100K | P23: Bachelor's degree
A24: Gambling managers | B24: 11-9071 | C24: 11 | D24: Line item | E24: 0.8299207 | F24: 5.1 | G24: 5.2 | H24: 0 | I24: 0 | J24: 0.1 | K24: 1.2 | L24: 7.7 | M24: 0.6 | N24: 85580 | O24: {=_xlfn.IFS(N24<45000,"Under 45K",N24<75000,"45K - 75K",N24<100000,"75K - 100K",N24>=100000,"Over 100K")} -> 75K - 100K | P24: High school diploma or equivalent
A25: Postmasters and mail superintendents | B25: 11-9131 | C25: 11 | D25: Line item | E25: 0.8233757 | F25: 13.1 | G25: 12.7 | H25: 0 | I25: 0 | J25: -0.5 | K25: -3.5 | L25: — | M25: 0.9 | N25: 92730 | O25: {=_xlfn.IFS(N25<45000,"Under 45K",N25<75000,"45K - 75K",N25<100000,"75K - 100K",N25>=100000,"Over 100K")} -> 75K - 100K | P25: High school diploma or equivalent
A26: General and operations managers | B26: 11-1021 | C26: 11 | D26: Line item | E26: 0.5748773 | F26: 3712.9 | G26: 3876.8 | H26: 2.2 | I26: 2.2 | J26: 164 | K26: 4.4 | L26: 0.9 | M26: 308.7 | N26: 102950 | O26: {=_xlfn.IFS(N26<45000,"Under 45K",N26<75000,"45K - 75K",N26<100000,"75K - 100K",N26>=100000,"Over 100K")} -> Over 100K | P26: Bachelor's degree
A27: Industrial production managers | B27: 11-3051 | C27: 11 | D27: Line item | E27: 0.5086878 | F27: 241.9 | G27: 246.5 | H27: 0.1 | I27: 0.1 | J27: 4.6 | K27: 1.9 | L27: 2.6 | M27: 17.1 | N27: 121440 | O27: {=_xlfn.IFS(N27<45000,"Under 45K",N27<75000,"45K - 75K",N27<100000,"75K - 100K",N27>=100000,"Over 100K")} -> Over 100K | P27: Bachelor's degree
A28: Lodging managers | B28: 11-9081 | C28: 11 | D28: Line item | E28: 0.4021726 | F28: 52 | G28: 53.8 | H28: 0 | I28: 0 | J28: 1.8 | K28: 3.4 | L28: 19.1 | M28: 5.4 | N28: 68130 | O28: {=_xlfn.IFS(N28<45000,"Under 45K",N28<75000,"45K - 75K",N28<100000,"75K - 100K",N28>=100000,"Over 100K")} -> 45K - 75K | P28: High school diploma or equivalent
A29: Education administrators, all other | B29: 11-9039 | C29: 11 | D29: Line item | E29: 0.3541265 | F29: 60.2 | G29: 61.7 | H29: 0 | I29: 0 | J29: 1.5 | K29: 2.5 | L29: 3.5 | M29: 4.1 | N29: 89040 | O29: {=_xlfn.IFS(N29<45000,"Under 45K",N29<75000,"45K - 75K",N29<100000,"75K - 100K",N29>=100000,"Over 100K")} -> 75K - 100K | P29: Bachelor's degree
A30: Legislators | B30: 11-1031 | C30: 11 | D30: Line item | E30: 0 | F30: 27.7 | G30: 28.6 | H30: 0 | I30: 0 | J30: 0.9 | K30: 3.4 | L30: — | M30: 2.2 | N30: 44810 | O30: {=_xlfn.IFS(N30<45000,"Under 45K",N30<75000,"45K - 75K",N30<100000,"75K - 100K",N30>=100000,"Over 100K")} -> Under 45K | P30: Bachelor's degree
A31: Public relations managers | B31: 11-2032 | C31: 11 | D31: Line item | E31: 0 | F31: 83.2 | G31: 87.3 | H31: 0 | I31: 0 | J31: 4.1 | K31: 5 | L31: 0.3 | M31: 6.6 | N31: 138520 | O31: {=_xlfn.IFS(N31<45000,"Under 45K",N31<75000,"45K - 75K",N31<100000,"75K - 100K",N31>=100000,"Over 100K")} -> Over 100K | P31: Bachelor's degree
A32: Fundraising managers | B32: 11-2033 | C32: 11 | D32: Line item | E32: 0 | F32: 45.7 | G32: 47.6 | H32: 0 | I32: 0 | J32: 1.9 | K32: 4.2 | L32: 0.2 | M32: 3.6 | N32: 123480 | O32: {=_xlfn.IFS(N32<45000,"Under 45K",N32<75000,"45K - 75K",N32<100000,"75K - 100K",N32>=100000,"Over 100K")} -> Over 100K | P32: Bachelor's degree
A33: Administrative services managers | B33: 11-3012 | C33: 11 | D33: Line item | E33: 0 | F33: 271.2 | G33: 283.8 | H33: 0.2 | I33: 0.2 | J33: 12.6 | K33: 4.6 | L33: 0 | M33: 23.2 | N33: 108390 | O33: {=_xlfn.IFS(N33<45000,"Under 45K",N33<75000,"45K - 75K",N33<100000,"75K - 100K",N33>=100000,"Over 100K")} -> Over 100K | P33: Bachelor's degree
A34: Facilities managers | B34: 11-3013 | C34: 11 | D34: Line item | E34: 0 | F34: 151.4 | G34: 157.1 | H34: 0.1 | I34: 0.1 | J34: 5.7 | K34: 3.8 | L34: — | M34: 13.2 | N34: 104690 | O34: {=_xlfn.IFS(N34<45000,"Under 45K",N34<75000,"45K - 75K",N34<100000,"75K - 100K",N34>=100000,"Over 100K")} -> Over 100K | P34: Bachelor's degree
A35: Entertainment and recreation managers, except gambling | B35: 11-9072 | C35: 11 | D35: Line item | E35: 0 | F35: 43.2 | G35: 46.5 | H35: 0 | I35: 0 | J35: 3.3 | K35: 7.7 | L35: 8.6 | M35: 5.5 | N35: 77180 | O35: {=_xlfn.IFS(N35<45000,"Under 45K",N35<75000,"45K - 75K",N35<100000,"75K - 100K",N35>=100000,"Over 100K")} -> 75K - 100K | P35: Bachelor's degree
A36: Funeral home managers | B36: 11-9171 | C36: 11 | D36: Line item | E36: 0 | F36: 32.1 | G36: 33.4 | H36: 0 | I36: 0 | J36: 1.3 | K36: 4.1 | L36: 56.1 | M36: 2.6 | N36: 76830 | O36: {=_xlfn.IFS(N36<45000,"Under 45K",N36<75000,"45K - 75K",N36<100000,"75K - 100K",N36>=100000,"Over 100K")} -> 75K - 100K | P36: Associate's degree
A37: Personal service managers, all other | B37: 11-9179 | C37: 11 | D37: Line item | E37: 0 | F37: 25.1 | G37: 26.7 | H37: 0 | I37: 0 | J37: 1.6 | K37: 6.5 | L37: 54.3 | M37: 2.1 | N37: 61340 | O37: {=_xlfn.IFS(N37<45000,"Under 45K",N37<75000,"45K - 75K",N37<100000,"75K - 100K",N37>=100000,"Over 100K")} -> 45K - 75K | P37: High school diploma or equivalent
A38: Food service managers | B38: 11-9051 | C38: 11 | D38: Line item | E38: -0.1213112 | F38: 352.8 | G38: 375.3 | H38: 0.2 | I38: 0.2 | J38: 22.6 | K38: 6.4 | L38: 30.3 | M38: 42 | N38: 65310 | O38: {=_xlfn.IFS(N38<45000,"Under 45K",N38<75000,"45K - 75K",N38<100000,"75K - 100K",N38>=100000,"Over 100K")} -> 45K - 75K | P38: High school diploma or equivalent
A39: Farmers, ranchers, and other agricultural managers | B39: 11-9013 | C39: 11 | D39: Line item | E39: -0.1443684 | F39: 836.1 | G39: 825 | H39: 0.5 | I39: 0.5 | J39: -11.1 | K39: -1.3 | L39: 62.6 | M39: 85.5 | N39: 87980 | O39: {=_xlfn.IFS(N39<45000,"Under 45K",N39<75000,"45K - 75K",N39<100000,"75K - 100K",N39>=100000,"Over 100K")} -> 75K - 100K | P39: High school diploma or equivalent
A40: Financial examiners | B40: 13-2061 | C40: 13 | D40: Line item | E40: 1.526064 | F40: 65.1 | G40: 77.2 | H40: 0 | I40: 0 | J40: 12.1 | K40: 18.5 | L40: 0.4 | M40: 5.7 | N40: 90400 | O40: {=_xlfn.IFS(N40<45000,"Under 45K",N40<75000,"45K - 75K",N40<100000,"75K - 100K",N40>=100000,"Over 100K")} -> 75K - 100K | P40: Bachelor's degree
A41: Budget analysts | B41: 13-2031 | C41: 13 | D41: Line item | E41: 1.502988 | F41: 50.4 | G41: 51 | H41: 0 | I41: 0 | J41: 0.5 | K41: 1 | L41: — | M41: 3.1 | N41: 87930 | O41: {=_xlfn.IFS(N41<45000,"Under 45K",N41<75000,"45K - 75K",N41<100000,"75K - 100K",N41>=100000,"Over 100K")} -> 75K - 100K | P41: Bachelor's degree
A42: Accountants and auditors | B42: 13-2011 | C42: 13 | D42: Line item | E42: 1.481956 | F42: 1579.8 | G42: 1652.6 | H42: 0.9 | I42: 0.9 | J42: 72.8 | K42: 4.6 | L42: 4.6 | M42: 124.2 | N42: 81680 | O42: {=_xlfn.IFS(N42<45000,"Under 45K",N42<75000,"45K - 75K",N42<100000,"75K - 100K",N42>=100000,"Over 100K")} -> 75K - 100K | P42: Bachelor's degree
A43: Compensation, benefits, and job analysis specialists | B43: 13-1141 | C43: 13 | D43: Line item | E43: 1.440985 | F43: 107 | G43: 112.7 | H43: 0.1 | I43: 0.1 | J43: 5.6 | K43: 5.3 | L43: — | M43: 8.5 | N43: 77020 | O43: {=_xlfn.IFS(N43<45000,"Under 45K",N43<75000,"45K - 75K",N43<100000,"75K - 100K",N43>=100000,"Over 100K")} -> 75K - 100K | P43: Bachelor's degree
A44: Management analysts | B44: 13-1111 | C44: 13 | D44: Line item | E44: 1.432417 | F44: 1075.1 | G44: 1169.7 | H44: 0.6 | I44: 0.7 | J44: 94.5 | K44: 8.8 | L44: 13.7 | M44: 98.1 | N44: 101190 | O44: {=_xlfn.IFS(N44<45000,"Under 45K",N44<75000,"45K - 75K",N44<100000,"75K - 100K",N44>=100000,"Over 100K")} -> Over 100K | P44: Bachelor's degree
A45: Market research analysts and marketing specialists | B45: 13-1161 | C45: 13 | D45: Line item | E45: 1.426757 | F45: 941.7 | G45: 1004.7 | H45: 0.6 | I45: 0.6 | J45: 63 | K45: 6.7 | L45: 5.9 | M45: 87.2 | N45: 76950 | O45: {=_xlfn.IFS(N45<45000,"Under 45K",N45<75000,"45K - 75K",N45<100000,"75K - 100K",N45>=100000,"Over 100K")} -> 75K - 100K | P45: Bachelor's degree
A46: Personal financial advisors | B46: 13-2052 | C46: 13 | D46: Line item | E46: 1.400749 | F46: 326 | G46: 357.2 | H46: 0.2 | I46: 0.2 | J46: 31.2 | K46: 9.6 | L46: 15.8 | M46: 24.1 | N46: 102140 | O46: {=_xlfn.IFS(N46<45000,"Under 45K",N46<75000,"45K - 75K",N46<100000,"75K - 100K",N46>=100000,"Over 100K")} -> Over 100K | P46: Bachelor's degree
A47: Loan officers | B47: 13-2072 | C47: 13 | D47: Line item | E47: 1.385739 | F47: 301.4 | G47: 306.5 | H47: 0.2 | I47: 0.2 | J47: 5 | K47: 1.7 | L47: 2.1 | M47: 20.3 | N47: 74180 | O47: {=_xlfn.IFS(N47<45000,"Under 45K",N47<75000,"45K - 75K",N47<100000,"75K - 100K",N47>=100000,"Over 100K")} -> 45K - 75K | P47: Bachelor's degree
A48: Credit counselors | B48: 13-2071 | C48: 13 | D48: Line item | E48: 1.385381 | F48: 31.8 | G48: 32.9 | H48: 0 | I48: 0 | J48: 1.1 | K48: 3.3 | L48: 1.4 | M48: 2.2 | N48: 50480 | O48: {=_xlfn.IFS(N48<45000,"Under 45K",N48<75000,"45K - 75K",N48<100000,"75K - 100K",N48>=100000,"Over 100K")} -> 45K - 75K | P48: Bachelor's degree
A49: Financial and investment analysts | B49: 13-2051 | C49: 13 | D49: Line item | E49: 1.380615 | F49: 368.5 | G49: 389.6 | H49: 0.2 | I49: 0.2 | J49: 21.1 | K49: 5.7 | L49: 5 | M49: 25.1 | N49: 101350 | O49: {=_xlfn.IFS(N49<45000,"Under 45K",N49<75000,"45K - 75K",N49<100000,"75K - 100K",N49>=100000,"Over 100K")} -> Over 100K | P49: Bachelor's degree
A50: Cost estimators | B50: 13-1051 | C50: 13 | D50: Line item | E50: 1.367669 | F50: 221.4 | G50: 212.1 | H50: 0.1 | I50: 0.1 | J50: -9.3 | K50: -4.2 | L50: 0.3 | M50: 16.9 | N50: 77070 | O50: {=_xlfn.IFS(N50<45000,"Under 45K",N50<75000,"45K - 75K",N50<100000,"75K - 100K",N50>=100000,"Over 100K")} -> 75K - 100K | P50: Bachelor's degree
A51: Tax examiners and collectors, and revenue agents | B51: 13-2081 | C51: 13 | D51: Line item | E51: 1.36682 | F51: 57.6 | G51: 56.5 | H51: 0 | I51: 0 | J51: -1 | K51: -1.8 | L51: — | M51: 4.3 | N51: 59740 | O51: {=_xlfn.IFS(N51<45000,"Under 45K",N51<75000,"45K - 75K",N51<100000,"75K - 100K",N51>=100000,"Over 100K")} -> 45K - 75K | P51: Bachelor's degree
A52: Financial specialists, all other | B52: 13-2099 | C52: 13 | D52: Line item | E52: 1.361362 | F52: 137.1 | G52: 141.4 | H52: 0.1 | I52: 0.1 | J52: 4.3 | K52: 3.1 | L52: 2.9 | M52: 10.3 | N52: 80190 | O52: {=_xlfn.IFS(N52<45000,"Under 45K",N52<75000,"45K - 75K",N52<100000,"75K - 100K",N52>=100000,"Over 100K")} -> 75K - 100K | P52: Bachelor's degree
A53: Human resources specialists | B53: 13-1071 | C53: 13 | D53: Line item | E53: 1.36005 | F53: 944.3 | G53: 1002.7 | H53: 0.6 | I53: 0.6 | J53: 58.4 | K53: 6.2 | L53: 0.5 | M53: 81.8 | N53: 72910 | O53: {=_xlfn.IFS(N53<45000,"Under 45K",N53<75000,"45K - 75K",N53<100000,"75K - 100K",N53>=100000,"Over 100K")} -> 45K - 75K | P53: Bachelor's degree
A54: Credit analysts | B54: 13-2041 | C54: 13 | D54: Line item | E54: 1.345268 | F54: 67.8 | G54: 64.8 | H54: 0 | I54: 0 | J54: -3 | K54: -4.4 | L54: — | M54: 3.7 | N54: 80970 | O54: {=_xlfn.IFS(N54<45000,"Under 45K",N54<75000,"45K - 75K",N54<100000,"75K - 100K",N54>=100000,"Over 100K")} -> 75K - 100K | P54: Bachelor's degree
A55: Labor relations specialists | B55: 13-1075 | C55: 13 | D55: Line item | E55: 1.334834 | F55: 65.4 | G55: 65.4 | H55: 0 | I55: 0 | J55: -0.1 | K55: -0.1 | L55: 0.5 | M55: 5.1 | N55: 93500 | O55: {=_xlfn.IFS(N55<45000,"Under 45K",N55<75000,"45K - 75K",N55<100000,"75K - 100K",N55>=100000,"Over 100K")} -> 75K - 100K | P55: Bachelor's degree
A56: Insurance underwriters | B56: 13-2053 | C56: 13 | D56: Line item | E56: 1.326652 | F56: 127 | G56: 123.7 | H56: 0.1 | I56: 0.1 | J56: -3.3 | K56: -2.6 | L56: — | M56: 8.2 | N56: 79880 | O56: {=_xlfn.IFS(N56<45000,"Under 45K",N56<75000,"45K - 75K",N56<100000,"75K - 100K",N56>=100000,"Over 100K")} -> 75K - 100K | P56: Bachelor's degree
A57: Logisticians | B57: 13-1081 | C57: 13 | D57: Line item | E57: 1.297303 | F57: 241 | G57: 281.3 | H57: 0.1 | I57: 0.2 | J57: 40.3 | K57: 16.7 | L57: 0.3 | M57: 26.4 | N57: 80880 | O57: {=_xlfn.IFS(N57<45000,"Under 45K",N57<75000,"45K - 75K",N57<100000,"75K - 100K",N57>=100000,"Over 100K")} -> 75K - 100K | P57: Bachelor's degree
A58: Tax preparers | B58: 13-2082 | C58: 13 | D58: Line item | E58: 1.29371 | F58: 90.6 | G58: 94.7 | H58: 0.1 | I58: 0.1 | J58: 4.1 | K58: 4.5 | L58: 15.5 | M58: 10.4 | N58: 50560 | O58: {=_xlfn.IFS(N58<45000,"Under 45K",N58<75000,"45K - 75K",N58<100000,"75K - 100K",N58>=100000,"Over 100K")} -> 45K - 75K | P58: High school diploma or equivalent
A59: Claims adjusters, examiners, and investigators | B59: 13-1031 | C59: 13 | D59: Line item | E59: 1.274024 | F59: 356.1 | G59: 337.9 | H59: 0.2 | I59: 0.2 | J59: -18.2 | K59: -5.1 | L59: 2.2 | M59: 21.1 | N59: 76790 | O59: {=_xlfn.IFS(N59<45000,"Under 45K",N59<75000,"45K - 75K",N59<100000,"75K - 100K",N59>=100000,"Over 100K")} -> 75K - 100K | P59: High school diploma or equivalent
A60: Fundraisers | B60: 13-1131 | C60: 13 | D60: Line item | E60: 1.242567 | F60: 134.4 | G60: 140.2 | H60: 0.1 | I60: 0.1 | J60: 5.8 | K60: 4.3 | L60: 1.9 | M60: 10.2 | N60: 66490 | O60: {=_xlfn.IFS(N60<45000,"Under 45K",N60<75000,"45K - 75K",N60<100000,"75K - 100K",N60>=100000,"Over 100K")} -> 45K - 75K | P60: Bachelor's degree
A61: Training and development specialists | B61: 13-1151 | C61: 13 | D61: Line item | E61: 1.198409 | F61: 452.3 | G61: 501 | H61: 0.3 | I61: 0.3 | J61: 48.7 | K61: 10.8 | L61: 0.5 | M61: 43.9 | N61: 65850 | O61: {=_xlfn.IFS(N61<45000,"Under 45K",N61<75000,"45K - 75K",N61<100000,"75K - 100K",N61>=100000,"Over 100K")} -> 45K - 75K | P61: Bachelor's degree
A62: Agents and business managers of artists, performers, and athletes | B62: 13-1011 | C62: 13 | D62: Line item | E62: 1.068559 | F62: 21.4 | G62: 23.2 | H62: 0 | I62: 0 | J62: 1.9 | K62: 8.7 | L62: 26.1 | M62: 2.2 | N62: 96310 | O62: {=_xlfn.IFS(N62<45000,"Under 45K",N62<75000,"45K - 75K",N62<100000,"75K - 100K",N62>=100000,"Over 100K")} -> 75K - 100K | P62: Bachelor's degree
A63: Business operations specialists, all other | B63: 13-1199 | C63: 13 | D63: Line item | E63: 1.047687 | F63: 1205.7 | G63: 1242 | H63: 0.7 | I63: 0.7 | J63: 36.3 | K63: 3 | L63: 1.4 | M63: 108.2 | N63: 81270 | O63: {=_xlfn.IFS(N63<45000,"Under 45K",N63<75000,"45K - 75K",N63<100000,"75K - 100K",N63>=100000,"Over 100K")} -> 75K - 100K | P63: Bachelor's degree
A64: Compliance officers | B64: 13-1041 | C64: 13 | D64: Line item | E64: 0.6981205 | F64: 418 | G64: 430.3 | H64: 0.2 | I64: 0.2 | J64: 12.3 | K64: 3 | L64: 0.4 | M64: 33.3 | N64: 78420 | O64: {=_xlfn.IFS(N64<45000,"Under 45K",N64<75000,"45K - 75K",N64<100000,"75K - 100K",N64>=100000,"Over 100K")} -> 75K - 100K | P64: Bachelor's degree
A65: Insurance appraisers, auto damage | B65: 13-1032 | C65: 13 | D65: Line item | E65: 0.6634955 | F65: 9.2 | G65: 8.4 | H65: 0 | I65: 0 | J65: -0.8 | K65: -8.2 | L65: 2.7 | M65: 0.5 | N65: 76650 | O65: {=_xlfn.IFS(N65<45000,"Under 45K",N65<75000,"45K - 75K",N65<100000,"75K - 100K",N65>=100000,"Over 100K")} -> 75K - 100K | P65: Postsecondary nondegree award
A66: Meeting, convention, and event planners | B66: 13-1121 | C66: 13 | D66: Line item | E66: 0.3740207 | F66: 155.8 | G66: 163.3 | H66: 0.1 | I66: 0.1 | J66: 7.5 | K66: 4.8 | L66: 5.1 | M66: 15.5 | N66: 59440 | O66: {=_xlfn.IFS(N66<45000,"Under 45K",N66<75000,"45K - 75K",N66<100000,"75K - 100K",N66>=100000,"Over 100K")} -> 45K - 75K | P66: Bachelor's degree
A67: Buyers and purchasing agents | B67: 13-1020 | C67: 13 | D67: Line item | E67: 0 | F67: 522.2 | G67: 552.3 | H67: 0.3 | I67: 0.3 | J67: 30.1 | K67: 5.8 | L67: 4.7 | M67: 52.2 | N67: 75650 | O67: {=_xlfn.IFS(N67<45000,"Under 45K",N67<75000,"45K - 75K",N67<100000,"75K - 100K",N67>=100000,"Over 100K")} -> 75K - 100K | P67: Bachelor's degree
A68: Project management specialists | B68: 13-1082 | C68: 13 | D68: Line item | E68: 0 | F68: 1046.3 | G68: 1105 | H68: 0.6 | I68: 0.6 | J68: 58.7 | K68: 5.6 | L68: 1.8 | M68: 78.2 | N68: 100750 | O68: {=_xlfn.IFS(N68<45000,"Under 45K",N68<75000,"45K - 75K",N68<100000,"75K - 100K",N68>=100000,"Over 100K")} -> Over 100K | P68: Bachelor's degree
... A70: Financial risk specialists | B70: 13-2054 | C70: 13 | D70: Line item | E70: 0 | F70: 60.5 | G70: 64.4 | H70: 0 | I70: 0 | J70: 3.9 | K70: 6.5 | L70: 4 | M70: 4.8 | N70: 106000 | O70: {=_xlfn.IFS(N70<45000,"Under 45K",N70<75000,"45K - 75K",N70<100000,"75K - 100K",N70>=100000,"Over 100K")} -> Over 100K | P70: Bachelor's degree
A71: Farm labor contractors | B71: 13-1074 | C71: 13 | D71: Line item | E71: -0.4354025 | F71: 3.9 | G71: 4.2 | H71: 0 | I71: 0 | J71: 0.2 | K71: 6 | L71: — | M71: 0.3 | N71: 48690 | O71: {=_xlfn.IFS(N71<45000,"Under 45K",N71<75000,"45K - 75K",N71<100000,"75K - 100K",N71>=100000,"Over 100K")} -> 45K - 75K | P71: No formal educational credential
A72: Actuaries | B72: 15-2011 | C72: 15 | D72: Line item | E72: 1.516474 | F72: 33.6 | G72: 40.9 | H72: 0 | I72: 0 | J72: 7.3 | K72: 21.8 | L72: — | M72: 2.4 | N72: 125770 | O72: {=_xlfn.IFS(N72<45000,"Under 45K",N72<75000,"45K - 75K",N72<100000,"75K - 100K",N72>=100000,"Over 100K")} -> Over 100K | P72: Bachelor's degree
A73: Mathematicians | B73: 15-2021 | C73: 15 | D73: Line item | E73: 1.472319 | F73: 2.4 | G73: 2.4 | H73: 0 | I73: 0 | J73: 0 | K73: -0.7 | L73: — | M73: 0.1 | N73: 121680 | O73: {=_xlfn.IFS(N73<45000,"Under 45K",N73<75000,"45K - 75K",N73<100000,"75K - 100K",N73>=100000,"Over 100K")} -> Over 100K | P73: Master's degree
A74: Operations research analysts | B74: 15-2031 | C74: 15 | D74: Line item | E74: 1.40002 | F74: 112.1 | G74: 136.2 | H74: 0.1 | I74: 0.1 | J74: 24.1 | K74: 21.5 | L74: — | M74: 9.6 | N74: 91290 | O74: {=_xlfn.IFS(N74<45000,"Under 45K",N74<75000,"45K - 75K",N74<100000,"75K - 100K",N74>=100000,"Over 100K")} -> 75K - 100K | P74: Bachelor's degree
A75: Statisticians | B75: 15-2041 | C75: 15 | D75: Line item | E75: 1.382724 | F75: 32.2 | G75: 34.9 | H75: 0 | I75: 0 | J75: 2.7 | K75: 8.5 | L75: 1.3 | M75: 2 | N75: 103300 | O75: {=_xlfn.IFS(N75<45000,"Under 45K",N75<75000,"45K - 75K",N75<100000,"75K - 100K",N75>=100000,"Over 100K")} -> Over 100K | P75: Master's degree
A76: Computer systems analysts | B76: 15-1211 | C76: 15 | D76: Line item | E76: 0 | F76: 521.1 | G76: 566.5 | H76: 0.3 | I76: 0.3 | J76: 45.5 | K76: 8.7 | L76: 2.2 | M76: 34.2 | N76: 103790 | O76: {=_xlfn.IFS(N76<45000,"Under 45K",N76<75000,"45K - 75K",N76<100000,"75K - 100K",N76>=100000,"Over 100K")} -> Over 100K | P76: Bachelor's degree
A77: Information security analysts | B77: 15-1212 | C77: 15 | D77: Line item | E77: 0 | F77: 182.8 | G77: 234.9 | H77: 0.1 | I77: 0.1 | J77: 52.1 | K77: 28.5 | L77: 0.6 | M77: 16 | N77: 124910 | O77: {=_xlfn.IFS(N77<45000,"Under 45K",N77<75000,"45K - 75K",N77<100000,"75K - 100K",N77>=100000,"Over 100K")} -> Over 100K | P77: Bachelor's degree
A78: Computer and information research scientists | B78: 15-1221 | C78: 15 | D78: Line item | E78: 0 | F78: 40.3 | G78: 48.3 | H78: 0 | I78: 0 | J78: 7.9 | K78: 19.7 | L78: 0.9 | M78: 3.2 | N78: 140910 | O78: {=_xlfn.IFS(N78<45000,"Under 45K",N78<75000,"45K - 75K",N78<100000,"75K - 100K",N78>=100000,"Over 100K")} -> Over 100K | P78: Master's degree
A79: Computer network support specialists | B79: 15-1231 | C79: 15 | D79: Line item | E79: 0 | F79: 152.7 | G79: 155.5 | H79: 0.1 | I79: 0.1 | J79: 2.8 | K79: 1.8 | L79: 2 | M79: 9.6 | N79: 73340 | O79: {=_xlfn.IFS(N79<45000,"Under 45K",N79<75000,"45K - 75K",N79<100000,"75K - 100K",N79>=100000,"Over 100K")} -> 45K - 75K | P79: Associate's degree
A80: Computer user support specialists | B80: 15-1232 | C80: 15 | D80: Line item | E80: 0 | F80: 729.5 | G80: 702.5 | H80: 0.4 | I80: 0.4 | J80: -27 | K80: -3.7 | L80: 2 | M80: 40.8 | N80: 60340 | O80: {=_xlfn.IFS(N80<45000,"Under 45K",N80<75000,"45K - 75K",N80<100000,"75K - 100K",N80>=100000,"Over 100K")} -> 45K - 75K | P80: Some college, no degree
A81: Computer network architects | B81: 15-1241 | C81: 15 | D81: Line item | E81: 0 | F81: 179.2 | G81: 200.6 | H81: 0.1 | I81: 0.1 | J81: 21.4 | K81: 11.9 | L81: 0.4 | M81: 11.2 | N81: 130390 | O81: {=_xlfn.IFS(N81<45000,"Under 45K",N81<75000,"45K - 75K",N81<100000,"75K - 100K",N81>=100000,"Over 100K")} -> Over 100K | P81: Bachelor's degree
A82: Database administrators | B82: 15-1242 | C82: 15 | D82: Line item | E82: 0 | F82: 78 | G82: 77.5 | H82: 0 | I82: 0 | J82: -0.5 | K82: -0.7 | L82: 1.2 | M82: 3.8 | N82: 104620 | O82: {=_xlfn.IFS(N82<45000,"Under 45K",N82<75000,"45K - 75K",N82<100000,"75K - 100K",N82>=100000,"Over 100K")} -> Over 100K | P82: Bachelor's degree
A83: Database architects | B83: 15-1243 | C83: 15 | D83: Line item | E83: 0 | F83: 66.9 | G83: 72.7 | H83: 0 | I83: 0 | J83: 5.8 | K83: 8.7 | L83: 1.4 | M83: 4 | N83: 135980 | O83: {=_xlfn.IFS(N83<45000,"Under 45K",N83<75000,"45K - 75K",N83<100000,"75K - 100K",N83>=100000,"Over 100K")} -> Over 100K | P83: Bachelor's degree
A84: Network and computer systems administrators | B84: 15-1244 | C84: 15 | D84: Line item | E84: 0 | F84: 331.5 | G84: 317.7 | H84: 0.2 | I84: 0.2 | J84: -13.8 | K84: -4.2 | L84: 0.3 | M84: 14.3 | N84: 96800 | O84: {=_xlfn.IFS(N84<45000,"Under 45K",N84<75000,"45K - 75K",N84<100000,"75K - 100K",N84>=100000,"Over 100K")} -> 75K - 100K | P84: Bachelor's degree
A85: Computer programmers | B85: 15-1251 | C85: 15 | D85: Line item | E85: 0 | F85: 121.2 | G85: 113.9 | H85: 0.1 | I85: 0.1 | J85: -7.2 | K85: -6 | L85: 6.2 | M85: 5.5 | N85: 98670 | O85: {=_xlfn.IFS(N85<45000,"Under 45K",N85<75000,"45K - 75K",N85<100000,"75K - 100K",N85>=100000,"Over 100K")} -> 75K - 100K | P85: Bachelor's degree
A86: Software developers | B86: 15-1252 | C86: 15 | D86: Line item | E86: 0 | F86: 1693.8 | G86: 1961.4 | H86: 1 | I86: 1.1 | J86: 267.7 | K86: 15.8 | L86: 1.6 | M86: 115.2 | N86: 133080 | O86: {=_xlfn.IFS(N86<45000,"Under 45K",N86<75000,"45K - 75K",N86<100000,"75K - 100K",N86>=100000,"Over 100K")} -> Over 100K | P86: Bachelor's degree
... A103: Architects, except landscape and naval | B103: 17-1011 | C103: 17 | D103: Line item | E103: 1.047142 | F103: 123.6 | G103: 128.4 | H103: 0.1 | I103: 0.1 | J103: 4.8 | K103: 3.9 | L103: 10.5 | M103: 7.8 | N103: 96690 | O103: {=_xlfn.IFS(N103<45000,"Under 45K",N103<75000,"45K - 75K",N103<100000,"75K - 100K",N103>=100000,"Over 100K")} -> 75K - 100K | P103: Bachelor's degree
A104: Materials engineers | B104: 17-2131 | C104: 17 | D104: Line item | E104: 1.037278 | F104: 23 | G104: 24.3 | H104: 0 | I104: 0 | J104: 1.3 | K104: 5.7 | L104: — | M104: 1.5 | N104: 108310 | O104: {=_xlfn.IFS(N104<45000,"Under 45K",N104<75000,"45K - 75K",N104<100000,"75K - 100K",N104>=100000,"Over 100K")} -> Over 100K | P104: Bachelor's degree
A105: Landscape architects | B105: 17-1012 | C105: 17 | D105: Line item | E105: 1.034388 | F105: 21.8 | G105: 22.6 | H105: 0 | I105: 0 | J105: 0.8 | K105: 3.5 | L105: 10.4 | M105: 1.7 | N105: 79660 | O105: {=_xlfn.IFS(N105<45000,"Under 45K",N105<75000,"45K - 75K",N105<100000,"75K - 100K",N105>=100000,"Over 100K")} -> 75K - 100K | P105: Bachelor's degree
A106: Mechanical engineers | B106: 17-2141 | C106: 17 | D106: Line item | E106: 1.004709 | F106: 293.1 | G106: 319.6 | H106: 0.2 | I106: 0.2 | J106: 26.5 | K106: 9.1 | L106: 1.2 | M106: 18.1 | N106: 102320 | O106: {=_xlfn.IFS(N106<45000,"Under 45K",N106<75000,"45K - 75K",N106<100000,"75K - 100K",N106>=100000,"Over 100K")} -> Over 100K | P106: Bachelor's degree
A107: Health and safety engineers, except mining safety engineers and inspectors | B107: 17-2111 | C107: 17 | D107: Line item | E107: 0.9948935 | F107: 23.8 | G107: 24.9 | H107: 0 | I107: 0 | J107: 1.1 | K107: 4.4 | L107: — | M107: 1.5 | N107: 109660 | O107: {=_xlfn.IFS(N107<45000,"Under 45K",N107<75000,"45K - 75K",N107<100000,"75K - 100K",N107>=100000,"Over 100K")} -> Over 100K | P107: Bachelor's degree
A108: Bioengineers and biomedical engineers | B108: 17-2031 | C108: 17 | D108: Line item | E108: 0.9874239 | F108: 22.2 | G108: 23.3 | H108: 0 | I108: 0 | J108: 1.1 | K108: 5.2 | L108: 0.2 | M108: 1.3 | N108: 106950 | O108: {=_xlfn.IFS(N108<45000,"Under 45K",N108<75000,"45K - 75K",N108<100000,"75K - 100K",N108>=100000,"Over 100K")} -> Over 100K | P108: Bachelor's degree
A109: Agricultural engineers | B109: 17-2021 | C109: 17 | D109: Line item | E109: 0.9409636 | F109: 1.7 | G109: 1.8 | H109: 0 | I109: 0 | J109: 0.1 | K109: 5.9 | L109: — | M109: 0.1 | N109: 84630 | O109: {=_xlfn.IFS(N109<45000,"Under 45K",N109<75000,"45K - 75K",N109<100000,"75K - 100K",N109>=100000,"Over 100K")} -> 75K - 100K | P109: Bachelor's degree
A110: Civil engineering technologists and technicians | B110: 17-3022 | C110: 17 | D110: Line item | E110: 0.9323219 | F110: 64.9 | G110: 66.2 | H110: 0 | I110: 0 | J110: 1.4 | K110: 2.1 | L110: 0.8 | M110: 5.5 | N110: 64200 | O110: {=_xlfn.IFS(N110<45000,"Under 45K",N110<75000,"45K - 75K",N110<100000,"75K - 100K",N110>=100000,"Over 100K")} -> 45K - 75K | P110: Associate's degree
A111: Architectural and civil drafters | B111: 17-3011 | C111: 17 | D111: Line item | E111: 0.9233925 | F111: 110.5 | G111: 115.1 | H111: 0.1 | I111: 0.1 | J111: 4.6 | K111: 4.1 | L111: 0.7 | M111: 10 | N111: 64280 | O111: {=_xlfn.IFS(N111<45000,"Under 45K",N111<75000,"45K - 75K",N111<100000,"75K - 100K",N111>=100000,"Over 100K")} -> 45K - 75K | P111: Associate's degree
A112: Electrical and electronics drafters | B112: 17-3012 | C112: 17 | D112: Line item | E112: 0.910166 | F112: 21.6 | G112: 20.4 | H112: 0 | I112: 0 | J112: -1.2 | K112: -5.6 | L112: 6.6 | M112: 1.7 | N112: 73720 | O112: {=_xlfn.IFS(N112<45000,"Under 45K",N112<75000,"45K - 75K",N112<100000,"75K - 100K",N112>=100000,"Over 100K")} -> 45K - 75K | P112: Associate's degree
A113: Mechanical drafters | B113: 17-3013 | C113: 17 | D113: Line item | E113: 0.8410071 | F113: 42.9 | G113: 40.1 | H113: 0 | I113: 0 | J113: -2.8 | K113: -6.5 | L113: 6.6 | M113: 3.3 | N113: 68510 | O113: {=_xlfn.IFS(N113<45000,"Under 45K",N113<75000,"45K - 75K",N113<100000,"75K - 100K",N113>=100000,"Over 100K")} -> 45K - 75K | P113: Associate's degree
A114: Cartographers and photogrammetrists | B114: 17-1021 | C114: 17 | D114: Line item | E114: 0.8169979 | F114: 13.4 | G114: 14.3 | H114: 0 | I114: 0 | J114: 0.9 | K114: 6.4 | L114: 2.3 | M114: 1 | N114: 78380 | O114: {=_xlfn.IFS(N114<45000,"Under 45K",N114<75000,"45K - 75K",N114<100000,"75K - 100K",N114>=100000,"Over 100K")} -> 75K - 100K | P114: Bachelor's degree
A115: Engineers, all other | B115: 17-2199 | C115: 17 | D115: Line item | E115: 0.787566 | F115: 158.8 | G115: 162.1 | H115: 0.1 | I115: 0.1 | J115: 3.3 | K115: 2.1 | L115: 2.1 | M115: 9.3 | N115: 117750 | O115: {=_xlfn.IFS(N115<45000,"Under 45K",N115<75000,"45K - 75K",N115<100000,"75K - 100K",N115>=100000,"Over 100K")} -> Over 100K | P115: Bachelor's degree
A116: Electronics engineers, except computer | B116: 17-2072 | C116: 17 | D116: Line item | E116: 0.6654578 | F116: 95.9 | G116: 101.8 | H116: 0.1 | I116: 0.1 | J116: 6 | K116: 6.2 | L116: 0.9 | M116: 5.7 | N116: 127590 | O116: {=_xlfn.IFS(N116<45000,"Under 45K",N116<75000,"45K - 75K",N116<100000,"75K - 100K",N116>=100000,"Over 100K")} -> Over 100K | P116: Bachelor's degree
A117: Industrial engineering technologists and technicians | B117: 17-3026 | C117: 17 | D117: Line item | E117: 0.6106679 | F117: 74.6 | G117: 75.9 | H117: 0 | I117: 0 | J117: 1.3 | K117: 1.7 | L117: 1.5 | M117: 6.3 | N117: 64790 | O117: {=_xlfn.IFS(N117<45000,"Under 45K",N117<75000,"45K - 75K",N117<100000,"75K - 100K",N117>=100000,"Over 100K")} -> 45K - 75K | P117: Associate's degree
...

Sheet Education Analysis
A3: Typical education needed for entry | B3: Average of AIOE | C3: Average of Employment change, percent, 2024–34 | F3: Req. Educ | G3: Avg AIOE
A4: Associate's degree | B4: 0.11000384 | C4: 3.075 | F4: Master's | G4: 0.7691541
A5: Bachelor's degree | B5: 0.72416889 | C5: 4.1533708 | F5: PhD/Prof | G5: 0.73184606
A6: Doctoral or professional degree | B6: 0.73184606 | C6: 4.0452055 | F6: Bachelor's | G6: 0.72416889
A7: High school diploma or equivalent | B7: -0.36827607 | C7: -0.81840491 | F7: Some college | G7: 0.24170056
A8: Master's degree | B8: 0.7691541 | C8: 7.245 | F8: Associate's | G8: 0.11000384
A9: No formal educational credential | B9: -0.89510787 | C9: 0.26605505 | F9: Postsecondary | G9: -0.34911962
A10: Postsecondary nondegree award | B10: -0.34911962 | C10: 4.8156863 | F10: HS diploma | G10: -0.36827607
A11: Some college, no degree | B11: 0.24170056 | C11: -4.0285714 | F11: No formal | G11: -0.89510787
A12: Grand Total | B12: -0.018467281 | C12: 1.7447115

Sheet Wage Analysis
A1: Wage Range | B1: Count of Occupations | C1: Avg. AIOE | D1: Avg. AIOE ; AIOE > 0 | E1: Avg. % Growth | G1: Wage Range | H1: Avg AIOE | I1: Avg % Growth
A2: Under 45K | B2: =COUNTIF('Tbl 1.2'!N:N, "<45000") -> 184 | C2: =AVERAGEIFS('Tbl 1.2'!E:E, 'Tbl 1.2'!N:N, "<45000") -> -0.4618159 | D2: =AVERAGEIFS('Tbl 1.2'!E:E, 'Tbl 1.2'!N:N, "<45000", 'Tbl 1.2'!E:E, ">0") -> 0.5272374 | E2: =AVERAGEIF('Tbl 1.2'!O:O,A2,'Tbl 1.2'!K:K) -> -0.25163043 | G2: Under 45K | H2: -0.46182 | I2: -0.25163
A3: 45K - 75K | B3: =COUNTIFS('Tbl 1.2'!N:N, ">=45000", 'Tbl 1.2'!N:N, "<75000") -> 389 | C3: =AVERAGEIFS('Tbl 1.2'!E:E, 'Tbl 1.2'!N:N, ">=45000", 'Tbl 1.2'!N:N, "<75000") -> -0.21607648 | D3: =AVERAGEIFS('Tbl 1.2'!E:E, 'Tbl 1.2'!N:N, ">=45000", 'Tbl 1.2'!N:N, "<75000", 'Tbl 1.2'!E:E, ">0") -> 0.85050101 | E3: =AVERAGEIF('Tbl 1.2'!O:O,A3,'Tbl 1.2'!K:K) -> 0.88508997 | G3: 45K-75K | H3: -0.21608 | I3: 0.88509
A4: 75K - 100K | B4: =COUNTIFS('Tbl 1.2'!N:N, ">=75000", 'Tbl 1.2'!N:N, "<100000") -> 126 | C4: =AVERAGEIFS('Tbl 1.2'!E:E, 'Tbl 1.2'!N:N, ">=75000", 'Tbl 1.2'!N:N, "<100000") -> 0.59035071 | D4: =AVERAGEIFS('Tbl 1.2'!E:E, 'Tbl 1.2'!N:N, ">=75000", 'Tbl 1.2'!N:N, "<100000", 'Tbl 1.2'!E:E, ">0") -> 1.0325183 | E4: =AVERAGEIF('Tbl 1.2'!O:O,A4,'Tbl 1.2'!K:K) -> 3.434127 | G4: 75K-100K | H4: 0.590351 | I4: 3.434127
A5: Over 100K | B5: =COUNTIFS('Tbl 1.2'!N:N, ">=100000") -> 110 | C5: =AVERAGEIFS('Tbl 1.2'!E:E, 'Tbl 1.2'!N:N, ">100000") -> 0.74570021 | D5: =AVERAGEIFS('Tbl 1.2'!E:E, 'Tbl 1.2'!N:N, ">100000", 'Tbl 1.2'!E:E, ">0") -> 1.0946261 | E5: =AVERAGEIF('Tbl 1.2'!O:O,A5,'Tbl 1.2'!K:K) -> 5.4203008 | G5: Over 100K | H5: 0.7457 | I5: 5.420301

Sheet Avg AIOE by SOC Category
A1: SOC Code Category | B1: Average of AIOE | C1: Average of Employment change, numeric, 2024–34 | D1: Average of Employment change, percent, 2024–34 | F1: SOC Code | G1: AVG AIOE
A2: 23 | B2: 1.2083207 | C2: 4.8 | D2: 1.7125 | F2: 23 | G2: 1.2083207 | S2: SOC Category Reference Key
A3: 13 | B3: 1.0484 | C3: 18.33125 | D3: 4.1125 | F3: 13 | G3: 1.0484 | R3: High AIOE/Cognitive | T3: Low AIOE/ Physical & Care Based
A4: 25 | B4: 0.84794969 | C4: 0.9703125 | D4: 1.9125 | F4: 25 | G4: 0.84794969 | R4: 23:Legal | T4: 29:Healthcare Prac
A5: 11 | B5: 0.77184447 | C5: 21.934211 | D5: 4.5394737 | F5: 11 | G5: 0.77184447 | R5: 13:Business & Finance | T5: 31: Healthcare Support
A6: 17 | B6: 0.76335121 | C6: 3.8888889 | D6: 3.2555556 | F6: 17 | G6: 0.76335121 | R6: 15: Computer & Math | T6: 35: Food Prep & Service
A7: 19 | B7: 0.70422783 | C7: 1.68125 | D7: 3.3833333 | F7: 19 | G7: 0.70422783 | R7: 25: Educational/Inst. | T7: 47: Construction
A8: 43 | B8: 0.6227622 | C8: -14.109259 | D8: -6.3962963 | F8: 43 | G8: 0.6227622 | R8: 43: Office & Admin | T8: 51: Production
A9: 21 | B9: 0.58164399 | C9: 12.482353 | D9: 6.1588235 | F9: 21 | G9: 0.58164399
A10: 41 | B10: 0.5490306 | C10: -13.536364 | D10: -1.1136364 | F10: 41 | G10: 0.5490306
A11: 15 | B11: 0.2748351 | C11: 25.985714 | D11: 9.6095238 | F11: 15 | G11: 0.2748351
A12: 27 | B12: 0.13875208 | C12: 2.0365854 | D12: 1.7073171 | F12: 27 | G12: 0.13875208
A13: 29 | B13: 0.056833938 | C13: 10.242254 | D13: 7.115493 | F13: 29 | G13: 0.056833938
A14: 31 | B14: -0.29401576 | C14: 58.135294 | D14: 7.4 | F14: 31 | G14: -0.29401576
A15: 33 | B15: -0.31416233 | C15: 1.2083333 | D15: 1.3041667 | F15: 33 | G15: -0.31416233
A16: 39 | B16: -0.3242978 | C16: 5.825 | D16: 3.8 | F16: 39 | G16: -0.3242978
A17: 53 | B17: -0.55919109 | C17: 11.59 | D17: 2.318 | F17: 53 | G17: -0.55919109
A18: 35 | B18: -0.66095135 | C18: 28.823529 | D18: 2.5764706 | F18: 35 | G18: -0.66095135
A19: 51 | B19: -0.74760733 | C19: -0.95047619 | D19: -4.9904762 | F19: 51 | G19: -0.74760733
A20: 45 | B20: -0.77993136 | C20: -1.8 | D20: -1.4785714 | F20: 45 | G20: -0.77993136
... A24: Grand Total | B24: -0.018467281 | C24: 6.2628606 | D24: 1.7447115 | F24: Grand Total | G24: -0.018467281
F26: SOC Code | G26: %Avg Change '24-'24
F27: 23 | G27: 1.7125
F28: 13 | G28: 4.1125
F29: 25 | G29: 1.9125
F30: 11 | G30: 4.5394737
F31: 17 | G31: 3.2555556
F32: 19 | G32: 3.3833333
F33: 43 | G33: -6.3962963
F34: 21 | G34: 6.1588235
F35: 41 | G35: -1.1136364
F36: 15 | G36: 9.6095238
F37: 27 | G37: 1.7073171
F38: 29 | G38: 7.115493
... F48: 47 | G48: 1.87

Sheet AIOE Appendix A
A1: SOC Code | B1: Occupation Title | C1: AIOE
A2: 11-1011 | B2: Chief Executives | C2: 1.334246
A3: 11-1021 | B3: General and Operations Managers | C3: 0.5748773
A4: 11-2011 | B4: Advertising and Promotions Managers | C4: 1.294387
A5: 11-2021 | B5: Marketing Managers | C5: 1.315032
A6: 11-2022 | B6: Sales Managers | C6: 1.26628
A7: 11-2031 | B7: Public Relations Managers | C7: 1.293689
A8: 11-3011 | B8: Administrative Services Managers | C8: 0.7398278
A9: 11-3021 | B9: Computer and Information Systems Managers | C9: 1.059853
A10: 11-3031 | B10: Financial Managers | C10: 1.446232
A11: 11-3051 | B11: Industrial Production Managers | C11: 0.5086878
A12: 11-3061 | B12: Purchasing Managers | C12: 1.423426
A13: 11-3071 | B13: Transportation, Storage, and Distribution Managers | C13: 0.8907923
... A775: 53-7121 | B775: Tank Car, Truck, and Ship Loaders | C775: -1.38776
